ntropy_ai/__init__.py
ntropy_ai/core/__init__.py
ntropy_ai/core/auth/__init__.py
ntropy_ai/core/document_instance/__init__.py
ntropy_ai/core/document_instance/load/__init__.py
ntropy_ai/core/document_instance/load/html.py
ntropy_ai/core/document_instance/load/json.py
ntropy_ai/core/document_instance/load/pdf.py
ntropy_ai/core/document_instance/process/__init__.py
ntropy_ai/core/document_instance/process/chunk_text.py
ntropy_ai/core/providers/__init__.py
ntropy_ai/core/providers/anthropic.py
ntropy_ai/core/providers/aws.py
ntropy_ai/core/providers/ollama.py
ntropy_ai/core/providers/openai.py
ntropy_ai/core/providers/pinecone.py
ntropy_ai/core/utils/__init__.py
ntropy_ai/core/utils/auth_format.py
ntropy_ai/core/utils/base_format.py
ntropy_ai/core/utils/chat/__init__.py
ntropy_ai/core/utils/chat/format.py
ntropy_ai/core/utils/connections_manager.py
ntropy_ai/core/utils/prompt.py
ntropy_ai/core/utils/settings.py
ntropy_ai-0.0.7a0.dist-info/LICENSE.txt
ntropy_ai-0.0.7a0.dist-info/METADATA
ntropy_ai-0.0.7a0.dist-info/WHEEL
ntropy_ai-0.0.7a0.dist-info/RECORD
