Metadata-Version: 2.1
Name: ntropy-ai
Version: 0.0.7a0
Summary: Unleash the power of multimodal agents
License: AGPL-3.0
Author: Hugo Le Belzic
Author-email: hugolebelzic@gmail.com
Requires-Python: >=3.10,<4.0
Classifier: License :: OSI Approved :: GNU Affero General Public License v3
Classifier: Programming Language :: Python :: 3
Classifier: Programming Language :: Python :: 3.10
Classifier: Programming Language :: Python :: 3.11
Classifier: Programming Language :: Python :: 3.12
Provides-Extra: document-instance-html
Provides-Extra: document-instance-pdf
Provides-Extra: providers-anthropic
Provides-Extra: providers-aws
Provides-Extra: providers-ollama
Provides-Extra: providers-openai
Provides-Extra: rag-vectorstore-pinecone
Requires-Dist: Pillow (==10.4.0)
Requires-Dist: boto3 (==1.34.140) ; extra == "providers-aws"
Requires-Dist: botocore (==1.34.140) ; extra == "providers-aws"
Requires-Dist: cryptography (==42.0.7)
Requires-Dist: ollama (==0.2.1) ; extra == "providers-ollama"
Requires-Dist: openai (==1.35.10) ; extra == "providers-openai"
Requires-Dist: opensearch-py (==2.6.0) ; extra == "providers-aws"
Requires-Dist: pinecone-client (==4.1.2) ; extra == "rag-vectorstore-pinecone"
Requires-Dist: pydantic (==2.8.2)
Requires-Dist: pymupdf (==1.24.7) ; extra == "document-instance-pdf"
Requires-Dist: tabulate (==0.9.0)
Requires-Dist: torch (==2.3.1) ; extra == "providers-openai"
Requires-Dist: torchvision (==0.18.1) ; extra == "providers-openai"
